{
  "_feature_order": [
    "man",
    "woman",
    "hair_blond",
    "hair_brown",
    "hair_black",
    "hair_red",
    "hair_white",
    "bald",
    "mustache",
    "beard",
    "glasses",
    "hat",
    "earrings"
  ],
  "Alex": {
    "characteristics": [
      "man",
      "black hair",
      "mustache"
    ],
    "features": {
      "man": 1,
      "woman": 0,
      "hair_blond": 0,
      "hair_brown": 0,
      "hair_black": 1,
      "hair_red": 0,
      "hair_white": 0,
      "bald": 0,
      "mustache": 1,
      "beard": 0,
      "glasses": 0,
      "hat": 0,
      "earrings": 0
    },
    "vector": [
      1,
      0,
      0,
      0,
      1,
      0,
      0,
      0,
      1,
      0,
      0,
      0,
      0
    ]
  },
  "Alfred": {
    "characteristics": [
      "man",
      "red hair",
      "mustache"
    ],
    "features": {
      "man": 1,
      "woman": 0,
      "hair_blond": 0,
      "hair_brown": 0,
      "hair_black": 0,
      "hair_red": 1,
      "hair_white": 0,
      "bald": 0,
      "mustache": 1,
      "beard": 0,
      "glasses": 0,
      "hat": 0,
      "earrings": 0
    },
    "vector": [
      1,
      0,
      0,
      0,
      0,
      1,
      0,
      0,
      1,
      0,
      0,
      0,
      0
    ]
  },
  "Anita": {
    "characteristics": [
      "woman",
      "blond hair"
    ],
    "features": {
      "man": 0,
      "woman": 1,
      "hair_blond": 1,
      "hair_brown": 0,
      "hair_black": 0,
      "hair_red": 0,
      "hair_white": 0,
      "bald": 0,
      "mustache": 0,
      "beard": 0,
      "glasses": 0,
      "hat": 0,
      "earrings": 0
    },
    "vector": [
      0,
      1,
      1,
      0,
      0,
      0,
      0,
      0,
      0,
      0,
      0,
      0,
      0
    ]
  },
  "Anne": {
    "characteristics": [
      "woman",
      "black hair",
      "earrings"
    ],
    "features": {
      "man": 0,
      "woman": 1,
      "hair_blond": 0,
      "hair_brown": 0,
      "hair_black": 1,
      "hair_red": 0,
      "hair_white": 0,
      "bald": 0,
      "mustache": 0,
      "beard": 0,
      "glasses": 0,
      "hat": 0,
      "earrings": 1
    },
    "vector": [
      0,
      1,
      0,
      0,
      1,
      0,
      0,
      0,
      0,
      0,
      0,
      0,
      1
    ]
  },
  "Bernard": {
    "characteristics": [
      "man",
      "brown hair",
      "hat"
    ],
    "features": {
      "man": 1,
      "woman": 0,
      "hair_blond": 0,
      "hair_brown": 1,
      "hair_black": 0,
      "hair_red": 0,
      "hair_white": 0,
      "bald": 0,
      "mustache": 0,
      "beard": 0,
      "glasses": 0,
      "hat": 1,
      "earrings": 0
    },
    "vector": [
      1,
      0,
      0,
      1,
      0,
      0,
      0,
      0,
      0,
      0,
      0,
      1,
      0
    ]
  },
  "Bill": {
    "characteristics": [
      "man",
      "bald",
      "beard"
    ],
    "features": {
      "man": 1,
      "woman": 0,
      "hair_blond": 0,
      "hair_brown": 0,
      "hair_black": 0,
      "hair_red": 1,
      "hair_white": 0,
      "bald": 1,
      "mustache": 0,
      "beard": 1,
      "glasses": 0,
      "hat": 0,
      "earrings": 0
    },
    "vector": [
      1,
      0,
      0,
      0,
      0,
      1,
      0,
      1,
      0,
      1,
      0,
      0,
      0
    ]
  },
  "Charles": {
    "characteristics": [
      "man",
      "blond hair",
      "mustache"
    ],
    "features": {
      "man": 1,
      "woman": 0,
      "hair_blond": 1,
      "hair_brown": 0,
      "hair_black": 0,
      "hair_red": 0,
      "hair_white": 0,
      "bald": 0,
      "mustache": 1,
      "beard": 0,
      "glasses": 0,
      "hat": 0,
      "earrings": 0
    },
    "vector": [
      1,
      0,
      1,
      0,
      0,
      0,
      0,
      0,
      1,
      0,
      0,
      0,
      0
    ]
  },
  "Claire": {
    "characteristics": [
      "woman",
      "red hair",
      "glasses",
      "hat",
      "earrings"
    ],
    "features": {
      "man": 0,
      "woman": 1,
      "hair_blond": 0,
      "hair_brown": 0,
      "hair_black": 0,
      "hair_red": 1,
      "hair_white": 0,
      "bald": 0,
      "mustache": 0,
      "beard": 0,
      "glasses": 1,
      "hat": 1,
      "earrings": 1
    },
    "vector": [
      0,
      1,
      0,
      0,
      0,
      1,
      0,
      0,
      0,
      0,
      1,
      1,
      1
    ]
  },
  "David": {
    "characteristics": [
      "man",
      "blond hair",
      "beard"
    ],
    "features": {
      "man": 1,
      "woman": 0,
      "hair_blond": 1,
      "hair_brown": 0,
      "hair_black": 0,
      "hair_red": 0,
      "hair_white": 0,
      "bald": 0,
      "mustache": 0,
      "beard": 1,
      "glasses": 0,
      "hat": 0,
      "earrings": 0
    },
    "vector": [
      1,
      0,
      1,
      0,
      0,
      0,
      0,
      0,
      0,
      1,
      0,
      0,
      0
    ]
  },
  "Eric": {
    "characteristics": [
      "man",
      "blond hair",
      "hat"
    ],
    "features": {
      "man": 1,
      "woman": 0,
      "hair_blond": 1,
      "hair_brown": 0,
      "hair_black": 0,
      "hair_red": 0,
      "hair_white": 0,
      "bald": 0,
      "mustache": 0,
      "beard": 0,
      "glasses": 0,
      "hat": 1,
      "earrings": 0
    },
    "vector": [
      1,
      0,
      1,
      0,
      0,
      0,
      0,
      0,
      0,
      0,
      0,
      1,
      0
    ]
  },
  "Frans": {
    "characteristics": [
      "man",
      "red hair"
    ],
    "features": {
      "man": 1,
      "woman": 0,
      "hair_blond": 0,
      "hair_brown": 0,
      "hair_black": 0,
      "hair_red": 1,
      "hair_white": 0,
      "bald": 0,
      "mustache": 0,
      "beard": 0,
      "glasses": 0,
      "hat": 0,
      "earrings": 0
    },
    "vector": [
      1,
      0,
      0,
      0,
      0,
      1,
      0,
      0,
      0,
      0,
      0,
      0,
      0
    ]
  },
  "George": {
    "characteristics": [
      "man",
      "white hair",
      "hat"
    ],
    "features": {
      "man": 1,
      "woman": 0,
      "hair_blond": 0,
      "hair_brown": 0,
      "hair_black": 0,
      "hair_red": 0,
      "hair_white": 1,
      "bald": 0,
      "mustache": 0,
      "beard": 0,
      "glasses": 0,
      "hat": 1,
      "earrings": 0
    },
    "vector": [
      1,
      0,
      0,
      0,
      0,
      0,
      1,
      0,
      0,
      0,
      0,
      1,
      0
    ]
  },
  "Herman": {
    "characteristics": [
      "man",
      "bald"
    ],
    "features": {
      "man": 1,
      "woman": 0,
      "hair_blond": 0,
      "hair_brown": 0,
      "hair_black": 0,
      "hair_red": 1,
      "hair_white": 0,
      "bald": 1,
      "mustache": 0,
      "beard": 0,
      "glasses": 0,
      "hat": 0,
      "earrings": 0
    },
    "vector": [
      1,
      0,
      0,
      0,
      0,
      1,
      0,
      1,
      0,
      0,
      0,
      0,
      0
    ]
  },
  "Joe": {
    "characteristics": [
      "man",
      "blond hair",
      "glasses"
    ],
    "features": {
      "man": 1,
      "woman": 0,
      "hair_blond": 1,
      "hair_brown": 0,
      "hair_black": 0,
      "hair_red": 0,
      "hair_white": 0,
      "bald": 0,
      "mustache": 0,
      "beard": 0,
      "glasses": 1,
      "hat": 0,
      "earrings": 0
    },
    "vector": [
      1,
      0,
      1,
      0,
      0,
      0,
      0,
      0,
      0,
      0,
      1,
      0,
      0
    ]
  },
  "Maria": {
    "characteristics": [
      "woman",
      "brown hair",
      "hat",
      "earrings"
    ],
    "features": {
      "man": 0,
      "woman": 1,
      "hair_blond": 0,
      "hair_brown": 1,
      "hair_black": 0,
      "hair_red": 0,
      "hair_white": 0,
      "bald": 0,
      "mustache": 0,
      "beard": 0,
      "glasses": 0,
      "hat": 1,
      "earrings": 1
    },
    "vector": [
      0,
      1,
      0,
      1,
      0,
      0,
      0,
      0,
      0,
      0,
      0,
      1,
      1
    ]
  },
  "Max": {
    "characteristics": [
      "man",
      "black hair",
      "mustache"
    ],
    "features": {
      "man": 1,
      "woman": 0,
      "hair_blond": 0,
      "hair_brown": 0,
      "hair_black": 1,
      "hair_red": 0,
      "hair_white": 0,
      "bald": 0,
      "mustache": 1,
      "beard": 0,
      "glasses": 0,
      "hat": 0,
      "earrings": 0
    },
    "vector": [
      1,
      0,
      0,
      0,
      1,
      0,
      0,
      0,
      1,
      0,
      0,
      0,
      0
    ]
  },
  "Paul": {
    "characteristics": [
      "man",
      "white hair",
      "glasses"
    ],
    "features": {
      "man": 1,
      "woman": 0,
      "hair_blond": 0,
      "hair_brown": 0,
      "hair_black": 0,
      "hair_red": 0,
      "hair_white": 1,
      "bald": 0,
      "mustache": 0,
      "beard": 0,
      "glasses": 1,
      "hat": 0,
      "earrings": 0
    },
    "vector": [
      1,
      0,
      0,
      0,
      0,
      0,
      1,
      0,
      0,
      0,
      1,
      0,
      0
    ]
  },
  "Peter": {
    "characteristics": [
      "man",
      "white hair"
    ],
    "features": {
      "man": 1,
      "woman": 0,
      "hair_blond": 0,
      "hair_brown": 0,
      "hair_black": 0,
      "hair_red": 0,
      "hair_white": 1,
      "bald": 0,
      "mustache": 0,
      "beard": 0,
      "glasses": 0,
      "hat": 0,
      "earrings": 0
    },
    "vector": [
      1,
      0,
      0,
      0,
      0,
      0,
      1,
      0,
      0,
      0,
      0,
      0,
      0
    ]
  },
  "Philip": {
    "characteristics": [
      "man",
      "black hair",
      "beard"
    ],
    "features": {
      "man": 1,
      "woman": 0,
      "hair_blond": 0,
      "hair_brown": 0,
      "hair_black": 1,
      "hair_red": 0,
      "hair_white": 0,
      "bald": 0,
      "mustache": 0,
      "beard": 1,
      "glasses": 0,
      "hat": 0,
      "earrings": 0
    },
    "vector": [
      1,
      0,
      0,
      0,
      1,
      0,
      0,
      0,
      0,
      1,
      0,
      0,
      0
    ]
  },
  "Richard": {
    "characteristics": [
      "man",
      "bald",
      "mustache",
      "beard"
    ],
    "features": {
      "man": 1,
      "woman": 0,
      "hair_blond": 0,
      "hair_brown": 1,
      "hair_black": 0,
      "hair_red": 0,
      "hair_white": 0,
      "bald": 1,
      "mustache": 1,
      "beard": 1,
      "glasses": 0,
      "hat": 0,
      "earrings": 0
    },
    "vector": [
      1,
      0,
      0,
      1,
      0,
      0,
      0,
      1,
      1,
      1,
      0,
      0,
      0
    ]
  },
  "Robert": {
    "characteristics": [
      "man",
      "brown hair"
    ],
    "features": {
      "man": 1,
      "woman": 0,
      "hair_blond": 0,
      "hair_brown": 1,
      "hair_black": 0,
      "hair_red": 0,
      "hair_white": 0,
      "bald": 0,
      "mustache": 0,
      "beard": 0,
      "glasses": 0,
      "hat": 0,
      "earrings": 0
    },
    "vector": [
      1,
      0,
      0,
      1,
      0,
      0,
      0,
      0,
      0,
      0,
      0,
      0,
      0
    ]
  },
  "Sam": {
    "characteristics": [
      "man",
      "bald",
      "glasses"
    ],
    "features": {
      "man": 1,
      "woman": 0,
      "hair_blond": 0,
      "hair_brown": 0,
      "hair_black": 0,
      "hair_red": 0,
      "hair_white": 1,
      "bald": 1,
      "mustache": 0,
      "beard": 0,
      "glasses": 1,
      "hat": 0,
      "earrings": 0
    },
    "vector": [
      1,
      0,
      0,
      0,
      0,
      0,
      1,
      1,
      0,
      0,
      1,
      0,
      0
    ]
  },
  "Susan": {
    "characteristics": [
      "woman",
      "white hair"
    ],
    "features": {
      "man": 0,
      "woman": 1,
      "hair_blond": 0,
      "hair_brown": 0,
      "hair_black": 0,
      "hair_red": 0,
      "hair_white": 1,
      "bald": 0,
      "mustache": 0,
      "beard": 0,
      "glasses": 0,
      "hat": 0,
      "earrings": 0
    },
    "vector": [
      0,
      1,
      0,
      0,
      0,
      0,
      1,
      0,
      0,
      0,
      0,
      0,
      0
    ]
  },
  "Tom": {
    "characteristics": [
      "man",
      "black hair",
      "bald",
      "glasses"
    ],
    "features": {
      "man": 1,
      "woman": 0,
      "hair_blond": 0,
      "hair_brown": 0,
      "hair_black": 1,
      "hair_red": 0,
      "hair_white": 0,
      "bald": 1,
      "mustache": 0,
      "beard": 0,
      "glasses": 1,
      "hat": 0,
      "earrings": 0
    },
    "vector": [
      1,
      0,
      0,
      0,
      1,
      0,
      0,
      1,
      0,
      0,
      1,
      0,
      0
    ]
  }
}
